{
  "id": "ASAS_Criteria_for_Axial_Spondyloarthritis_SpA_guideline.v1",
  "gdl_version": "2.0",
  "concept": "gt0001",
  "language": {
    "original_language": "ISO_639-1::en"
  },
  "description": {
    "original_author": {
      "date": "2020-06-03",
      "name": "Maryam Razavi",
      "organisation": "CambioCDS",
      "email": "maryam.razavi2009@gmail.com"
    },
    "lifecycle_state": "Author draft",
    "details": {
      "en": {
        "id": "en",
        "purpose": "Diagnoses axial spondyloarthritis according to assessment of Spondyloarthritis International Society (ASAS) criteria.\n",
        "keywords": [
          "Assessment of the SpondyloArthritis international Society (ASAS)",
          "Axial Spondyloarthritis",
          "Ankylosing spondylitis (AS)"
        ],
        "use": "ASAS Criteria for Axial Spondyloarthritis (SpA) can be used in patients who have had chronic back pain (for more than equal  3 months) of unknown origin (no definite diagnosis) that began before 45 years of age. ",
        "misuse": "ASAS criteria for axial spondyloarthritis (SpA) can not be used for patients who do not meet entry criteria and required criteria.  ",
        "copyright": "@CambioCDS"
      }
    },
    "other_details": {
      "references": "Primary Reference: \nRudwaleit M, Van Der Heijde D, Landewé R, Listing J, Akkoc N, Brandt J, Braun J, Chou CT, Collantes-Estevez E, Dougados M, Huang F. The development of Assessment of SpondyloArthritis international Society classification criteria for axial spondyloarthritis (part II): validation and final selection. Annals of the rheumatic diseases. 2009 Jun 1;68(6):777-83.\nClinical Practice Guidelines:\nWard MM, Deodhar A, Akl EA, Lui A, Ermann J, Gensler LS, Smith JA, Borenstein D, Hiratzka J, Weiss PF, Inman RD. American College of Rheumatology/Spondylitis Association of America/Spondyloarthritis Research and Treatment Network 2015 recommendations for the treatment of ankylosing spondylitis and nonradiographic axial spondyloarthritis. Arthritis & Rheumatology. 2016 Feb;68(2):282-98.\nOther references:\nLinden SV, Valkenburg HA, Cats A. Evaluation of diagnostic criteria for ankylosing spondylitis. Arthritis & Rheumatism. 1984 Apr;27(4):361-8."
    }
  },
  "definition": {
    "data_bindings": {
      "gt0002": {
        "id": "gt0002",
        "model_id": "openEHR-EHR-OBSERVATION.basic_demographic.v1",
        "template_id": "openEHR-EHR-OBSERVATION.basic_demographic.v1",
        "type": "INPUT",
        "elements": {
          "gt0003": {
            "id": "gt0003",
            "path": "/data[at0001]/events[at0002]/data[at0003]/items[at0013]"
          }
        }
      },
      "gt0004": {
        "id": "gt0004",
        "model_id": "openEHR-EHR-OBSERVATION.asas_criteria_for_axial_spondyloarthritis_spa.v0",
        "template_id": "openEHR-EHR-OBSERVATION.asas_criteria_for_axial_spondyloarthritis_spa.v0",
        "type": "OUTPUT",
        "elements": {
          "gt0035": {
            "id": "gt0035",
            "path": "/data[at0001]/events[at0002]/data[at0003]/items[at0053]"
          },
          "gt0066": {
            "id": "gt0066",
            "path": "/data[at0001]/events[at0002]/data[at0003]/items[at0061]"
          }
        }
      },
      "gt0038": {
        "id": "gt0038",
        "model_id": "openEHR-EHR-OBSERVATION.asas_criteria_for_axial_spondyloarthritis_spa.v0",
        "template_id": "openEHR-EHR-OBSERVATION.asas_criteria_for_axial_spondyloarthritis_spa.v0",
        "type": "INPUT",
        "elements": {
          "gt0041": {
            "id": "gt0041",
            "path": "/data[at0001]/events[at0002]/data[at0003]/items[at0004]/items[at0008]"
          },
          "gt0042": {
            "id": "gt0042",
            "path": "/data[at0001]/events[at0002]/data[at0003]/items[at0012]/items[at0013]"
          },
          "gt0043": {
            "id": "gt0043",
            "path": "/data[at0001]/events[at0002]/data[at0003]/items[at0012]/items[at0016]"
          },
          "gt0044": {
            "id": "gt0044",
            "path": "/data[at0001]/events[at0002]/data[at0003]/items[at0020]/items[at0021]"
          },
          "gt0045": {
            "id": "gt0045",
            "path": "/data[at0001]/events[at0002]/data[at0003]/items[at0020]/items[at0024]"
          },
          "gt0046": {
            "id": "gt0046",
            "path": "/data[at0001]/events[at0002]/data[at0003]/items[at0020]/items[at0029]"
          },
          "gt0047": {
            "id": "gt0047",
            "path": "/data[at0001]/events[at0002]/data[at0003]/items[at0020]/items[at0032]"
          },
          "gt0048": {
            "id": "gt0048",
            "path": "/data[at0001]/events[at0002]/data[at0003]/items[at0020]/items[at0035]"
          },
          "gt0049": {
            "id": "gt0049",
            "path": "/data[at0001]/events[at0002]/data[at0003]/items[at0020]/items[at0038]"
          },
          "gt0050": {
            "id": "gt0050",
            "path": "/data[at0001]/events[at0002]/data[at0003]/items[at0020]/items[at0041]"
          },
          "gt0051": {
            "id": "gt0051",
            "path": "/data[at0001]/events[at0002]/data[at0003]/items[at0020]/items[at0044]"
          },
          "gt0052": {
            "id": "gt0052",
            "path": "/data[at0001]/events[at0002]/data[at0003]/items[at0020]/items[at0047]"
          },
          "gt0054": {
            "id": "gt0054",
            "path": "/data[at0001]/events[at0002]/data[at0003]/items[at0020]/items[at0050]"
          }
        }
      }
    },
    "pre_conditions": [
      "$gt0003|Age at onset|<45,a",
      "$gt0041|Back pain|==1|local::at0010|>=3 months|"
    ],
    "rules": {
      "gt0081": {
        "id": "gt0081",
        "priority": 14,
        "then": [
          "$gt0035|SpA Score|.magnitude=0"
        ]
      },
      "gt0082": {
        "id": "gt0082",
        "priority": 13,
        "when": [
          "$gt0044|Inflammatory back pain|==1|local::at0023|Yes|"
        ],
        "then": [
          "$gt0035|SpA Score|.magnitude=$gt0035+1"
        ]
      },
      "gt0083": {
        "id": "gt0083",
        "priority": 12,
        "when": [
          "$gt0045|Arthritis|==1|local::at0028|Yes|"
        ],
        "then": [
          "$gt0035|SpA Score|.magnitude=$gt0035+1"
        ]
      },
      "gt0069": {
        "id": "gt0069",
        "priority": 11,
        "when": [
          "$gt0046|Enthesitis (heel)|==1|local::at0031|Yes|"
        ],
        "then": [
          "$gt0035|SpA Score|.magnitude=$gt0035+1"
        ]
      },
      "gt0070": {
        "id": "gt0070",
        "priority": 10,
        "when": [
          "$gt0047|Uveitis|==1|local::at0034|Yes|"
        ],
        "then": [
          "$gt0035|SpA Score|.magnitude=$gt0035+1"
        ]
      },
      "gt0071": {
        "id": "gt0071",
        "priority": 9,
        "when": [
          "$gt0048|Dactylitis|==1|local::at0037|Yes|"
        ],
        "then": [
          "$gt0035|SpA Score|.magnitude=$gt0035+1"
        ]
      },
      "gt0072": {
        "id": "gt0072",
        "priority": 8,
        "when": [
          "$gt0049|Psoriasis|==1|local::at0040|Yes|"
        ],
        "then": [
          "$gt0035|SpA Score|.magnitude=$gt0035+1"
        ]
      },
      "gt0073": {
        "id": "gt0073",
        "priority": 7,
        "when": [
          "$gt0050|Crohn’s disease or ulcerative colitis|==1|local::at0043|Yes|"
        ],
        "then": [
          "$gt0035|SpA Score|.magnitude=$gt0035+1"
        ]
      },
      "gt0074": {
        "id": "gt0074",
        "priority": 6,
        "when": [
          "$gt0051|Good response to NSAIDs|==1|local::at0046|Yes|"
        ],
        "then": [
          "$gt0035|SpA Score|.magnitude=$gt0035+1"
        ]
      },
      "gt0075": {
        "id": "gt0075",
        "priority": 5,
        "when": [
          "$gt0052|Family history of SpA|==1|local::at0049|Yes|"
        ],
        "then": [
          "$gt0035|SpA Score|.magnitude=$gt0035+1"
        ]
      },
      "gt0076": {
        "id": "gt0076",
        "priority": 4,
        "when": [
          "$gt0054|Elevated CRP|==1|local::at0052|Yes|"
        ],
        "then": [
          "$gt0035|SpA Score|.magnitude=$gt0035+1"
        ]
      },
      "gt0077": {
        "id": "gt0077",
        "priority": 3,
        "when": [
          "$gt0043|HLA-B27|==1|local::at0067|Yes|"
        ],
        "then": [
          "$gt0035|SpA Score|.magnitude=$gt0035+1"
        ]
      },
      "gt0079": {
        "id": "gt0079",
        "priority": 2,
        "when": [
          "$gt0042|Sacroiliitis on imaging|==1|local::at0065|Yes|",
          "$gt0035|SpA Score|>=1"
        ],
        "then": [
          "$gt0066|Diagnostic Result|=local::at0068|Axial SpA|"
        ]
      },
      "gt0080": {
        "id": "gt0080",
        "priority": 1,
        "when": [
          "$gt0042|Sacroiliitis on imaging|==0|local::at0064|No|",
          "$gt0043|HLA-B27|==1|local::at0067|Yes|",
          "$gt0035|SpA Score|>=3"
        ],
        "then": [
          "$gt0066|Diagnostic Result|=local::at0068|Axial SpA|"
        ]
      }
    }
  },
  "ontology": {
    "term_definitions": {
      "en": {
        "id": "en",
        "terms": {
          "gt0001": {
            "id": "gt0001",
            "text": "ASAS Criteria for Axial Spondyloarthritis (SpA)",
            "description": "ASAS refers to the assessment of the SpondyloArthritis international Society. Ankylosing spondylitis (AS) is a form of chronic inflammatory arthritis characterized by sacroiliitis, enthesitis, and a marked propensity for sacroiliac joint and spinal fusion.  AS is a condition in the spondyloarthritis (SpA) family of disease and distinguished by universal involvement with joint inflammation or fusion, and more prevalent spinal ankylosis. \nASAS criteria for axial spondyloarthritis (SpA) can be used for patients who meet entry criteria and required criteria.  \nEntry criteria: patients who have had chronic back pain (for more than equal  3 months) of unknown origin (no definite diagnosis) that began before 45 years of age. \n\nRequired criteria: Sacroiliitis on imaging (Note) plus ≥1 SpA feature, or\nHLA-B27 plus ≥2 additional SpA features. \n\nSpA features are including:  Inflammatory back pain, Arthritis, Enthesitis (heel), Uveitis, Dactylitis, Psoriasis, Crohn’s disease or ulcerative colitis, Good response to NSAIDs, Family history of SpA, HLA-B27, Elevated CRP. \n\nNote: \nSacroiliitis by radiographs refers to bilateral grade 2–4 or unilateral grade 3–4 sacroiliitis on plain radiographs, according to the modified New York criteria.\nSacroiliitis by MRI refers to active (acute) inflammatory lesions of sacroiliac joints with definite bone marrow oedema/osteitis, suggestive of sacroiliitis associated with SpA.\n\nASA classification for axial SpA and Diagnostic result:\n\npatient with back pain >=3 months and age <45 years= Yes, Sarcroiliitis on imaging=Yes , Diagnostic result= Not axial SpA\n\npatient with back pain >=3 months and age <45 years= Yes, Sarcroiliitis on imaging=Yes,  ≥1 SpA features= Yes, Diagnostic result= Axial SpA\n\npatient with back pain >=3 months and age <45 years= Yes, HLA-B27=Yes, Diagnostic result= Not axial SpA\n\npatient with back pain >=3 months and age <45 years= Yes, HLA-B27=Yes,  ≥2 SpA features other than HLA-B27 positive= Yes, Diagnostic result= Axial SpA\n\n\n\n"
          },
          "gt0003": {
            "id": "gt0003",
            "text": "Age at onset",
            "description": "Age in years, and for babies: months, weeks or days"
          },
          "gt0005": {
            "id": "gt0005",
            "text": "Age at onset ",
            "description": "*"
          },
          "gt0008": {
            "id": "gt0008",
            "text": "Age at onset ",
            "description": "*"
          },
          "gt0009": {
            "id": "gt0009",
            "text": "Back pain",
            "description": "*"
          },
          "gt0010": {
            "id": "gt0010",
            "text": "Sacroiliitis on imaging",
            "description": "*"
          },
          "gt0011": {
            "id": "gt0011",
            "text": "HLA-B27",
            "description": "*"
          },
          "gt0012": {
            "id": "gt0012",
            "text": "Inflammatory back pain",
            "description": "*"
          },
          "gt0013": {
            "id": "gt0013",
            "text": "Arthritis",
            "description": "*"
          },
          "gt0014": {
            "id": "gt0014",
            "text": "Enthesitis (heel)",
            "description": "*"
          },
          "gt0015": {
            "id": "gt0015",
            "text": "Uveitis",
            "description": "*"
          },
          "gt0016": {
            "id": "gt0016",
            "text": "Dactylitis",
            "description": "*"
          },
          "gt0017": {
            "id": "gt0017",
            "text": "Psoriasis",
            "description": "*"
          },
          "gt0018": {
            "id": "gt0018",
            "text": "Crohn’s disease or ulcerative colitis",
            "description": "*"
          },
          "gt0019": {
            "id": "gt0019",
            "text": "Good response to NSAIDs",
            "description": "*"
          },
          "gt0020": {
            "id": "gt0020",
            "text": "Family history of SpA",
            "description": "*"
          },
          "gt0021": {
            "id": "gt0021",
            "text": "Elevated CRP",
            "description": "*"
          },
          "gt0023": {
            "id": "gt0023",
            "text": "Sacroiliitis Score",
            "description": "*"
          },
          "gt0024": {
            "id": "gt0024",
            "text": "HLA-B27",
            "description": "*"
          },
          "gt0026": {
            "id": "gt0026",
            "text": "Diagnostic Result",
            "description": "*"
          },
          "gt0027": {
            "id": "gt0027",
            "text": "Set Age<45"
          },
          "gt0028": {
            "id": "gt0028",
            "text": "Set Back pain >=3 months"
          },
          "gt0029": {
            "id": "gt0029",
            "text": "Set Entry Criterion"
          },
          "gt0030": {
            "id": "gt0030",
            "text": "Entry Criterion Score",
            "description": "*"
          },
          "gt0031": {
            "id": "gt0031",
            "text": "Set Sacroiliitis on imaging"
          },
          "gt0032": {
            "id": "gt0032",
            "text": "Set SpA Features for Sacroiliitis on imaging"
          },
          "gt0033": {
            "id": "gt0033",
            "text": "HLA-B27",
            "description": "*"
          },
          "gt0034": {
            "id": "gt0034",
            "text": "Elevated CRP",
            "description": "*"
          },
          "gt0035": {
            "id": "gt0035",
            "text": "SpA Score",
            "description": "*"
          },
          "gt0036": {
            "id": "gt0036",
            "text": "HLA-B27",
            "description": "*"
          },
          "gt0039": {
            "id": "gt0039",
            "text": "Sacroiliitis on imaging",
            "description": "*"
          },
          "gt0040": {
            "id": "gt0040",
            "text": "HLA-B27",
            "description": "*"
          },
          "gt0041": {
            "id": "gt0041",
            "text": "Back pain",
            "description": "*"
          },
          "gt0042": {
            "id": "gt0042",
            "text": "Sacroiliitis on imaging",
            "description": "*"
          },
          "gt0043": {
            "id": "gt0043",
            "text": "HLA-B27",
            "description": "*"
          },
          "gt0044": {
            "id": "gt0044",
            "text": "Inflammatory back pain",
            "description": "*"
          },
          "gt0045": {
            "id": "gt0045",
            "text": "Arthritis",
            "description": "*"
          },
          "gt0046": {
            "id": "gt0046",
            "text": "Enthesitis (heel)",
            "description": "*"
          },
          "gt0047": {
            "id": "gt0047",
            "text": "Uveitis",
            "description": "*"
          },
          "gt0048": {
            "id": "gt0048",
            "text": "Dactylitis",
            "description": "*"
          },
          "gt0049": {
            "id": "gt0049",
            "text": "Psoriasis",
            "description": "*"
          },
          "gt0050": {
            "id": "gt0050",
            "text": "Crohn’s disease or ulcerative colitis",
            "description": "*"
          },
          "gt0051": {
            "id": "gt0051",
            "text": "Good response to NSAIDs",
            "description": "*"
          },
          "gt0052": {
            "id": "gt0052",
            "text": "Family history of SpA",
            "description": "*"
          },
          "gt0053": {
            "id": "gt0053",
            "text": "HLA-B27",
            "description": "*"
          },
          "gt0054": {
            "id": "gt0054",
            "text": "Elevated CRP",
            "description": "*"
          },
          "gt0055": {
            "id": "gt0055",
            "text": "Set Entry Criterion"
          },
          "gt0056": {
            "id": "gt0056",
            "text": "Set Required Criteria"
          },
          "gt0057": {
            "id": "gt0057",
            "text": "Set SpA features for Sacroiliitis on imaging"
          },
          "gt0058": {
            "id": "gt0058",
            "text": "Set SpA feature for HLA-B27"
          },
          "gt0059": {
            "id": "gt0059",
            "text": "Set Axial SpA for Sacroiliitis on imaging"
          },
          "gt0060": {
            "id": "gt0060",
            "text": "Set Axial SpA for HLA-B27"
          },
          "gt0061": {
            "id": "gt0061",
            "text": "Set Not Axial SpA for Sacroiliitis on imaging"
          },
          "gt0062": {
            "id": "gt0062",
            "text": "Set Not Axial SpA for HLA-B27"
          },
          "gt0063": {
            "id": "gt0063",
            "text": "Set Not Axial"
          },
          "gt0064": {
            "id": "gt0064",
            "text": "Set Axial SpA to Sacroiliitis on imaging"
          },
          "gt0065": {
            "id": "gt0065",
            "text": "Set Axial SpA to HLA-B27"
          },
          "gt0066": {
            "id": "gt0066",
            "text": "Diagnostic Result",
            "description": "*"
          },
          "gt0067": {
            "id": "gt0067",
            "text": "SpA Score+ inflammatory back pain"
          },
          "gt0068": {
            "id": "gt0068",
            "text": "SpA Score+ Arthritis"
          },
          "gt0069": {
            "id": "gt0069",
            "text": "SpA Score+ Enthesitis (heel)"
          },
          "gt0070": {
            "id": "gt0070",
            "text": "SpA Score+ Uveitis"
          },
          "gt0071": {
            "id": "gt0071",
            "text": "SpA Score+ Dactylitis"
          },
          "gt0072": {
            "id": "gt0072",
            "text": "SpA Score+ Psoriasis"
          },
          "gt0073": {
            "id": "gt0073",
            "text": "SpA Score+ Crohn's disease or ulcerative colitis"
          },
          "gt0074": {
            "id": "gt0074",
            "text": "SpA Score+ Good response to NSAIDs"
          },
          "gt0075": {
            "id": "gt0075",
            "text": "SpA Score+ Family history of SpA"
          },
          "gt0076": {
            "id": "gt0076",
            "text": "SpA Score+ Elevated CRP"
          },
          "gt0077": {
            "id": "gt0077",
            "text": "SpA Score+ HLA-B27"
          },
          "gt0078": {
            "id": "gt0078",
            "text": "SpA Score"
          },
          "gt0079": {
            "id": "gt0079",
            "text": "Axial SpA, Sacroiliitis on imaging"
          },
          "gt0080": {
            "id": "gt0080",
            "text": "Axial SpA , HLA-B27"
          },
          "gt0081": {
            "id": "gt0081",
            "text": "SpA"
          },
          "gt0082": {
            "id": "gt0082",
            "text": "SpA Score +Inflammatory back pain"
          },
          "gt0083": {
            "id": "gt0083",
            "text": "SpA Score +Arthritis"
          },
          "gt0084": {
            "id": "gt0084",
            "text": "No Axial SpA"
          },
          "gt0085": {
            "id": "gt0085",
            "text": "Not Axial SpA, Sacroiliitis on imaging"
          },
          "gt0086": {
            "id": "gt0086",
            "text": "Not Axial SpA , HLA-B27"
          }
        }
      }
    }
  }
}