{
  "id": "SLEDAI-2K.v1",
  "gdl_version": "2.0",
  "concept": "gt0001",
  "language": {
    "original_language": "ISO_639-1::en"
  },
  "description": {
    "original_author": {
      "date": "2021-02-18",
      "name": "Therese Lindberg",
      "organisation": "Cambio CDS",
      "email": "therese.lindberg@cambio.se"
    },
    "lifecycle_state": "Initial",
    "details": {
      "en": {
        "id": "en",
        "purpose": "To calculate the SLEDAI-2K.",
        "keywords": [
          "systemic",
          "SLEDAI-2K",
          "seizure",
          "pscyhosis",
          "organic brain syndrome",
          "visual disturbance",
          "lupus headache",
          "stroke",
          "vasculitis",
          "arthritis",
          "myositis",
          "hematuria",
          "proteinuria",
          "pyuria",
          "inflammatory-type rash",
          "alopecia",
          "oral ulcers",
          "pericarditis",
          "temp",
          "platelets",
          "WBC",
          " lupus",
          " erythematosus",
          "disease",
          "2000",
          "index"
        ],
        "use": "Use to calculate SLEDAI-2K in order to stratify severity of systemic lupus erythematosus (SLE). The calculations are based on 24 parameters: \n1. Recent onset seizure: Exclude metabolic, infectious, or drug causes\n2. Psychosis: Altered ability to function in normal activity due to severe disturbance in the perception of reality (include hallucinations, incoherence, marked loose associations, impoverished thought content, marked illogical thinking, and bizarre, disorganized, or catatonic behavior); exclude uremia and drug causes\n3. Organic brain syndrome: Altered mental function with impaired orientation, memory, or other intellectual function (with rapid onset and fluctuating clinical features), inability to sustain attention to environment, and ≥2 of the following: perceptual disturbance, incoherent speech, insomnia or daytime drowsiness, and increased or decreased psychomotor activity; exclude metabolic, infectious, or drug causes.\n4. Visual disturbance: Retinal changes of SLE (include cytoid bodies, retinal hemorrhages, serous exudates or hemorrhages in choroid, and optic neuritis); exclude hypertensive, infectious, or drug causes.\n5. New onset sensory or motor neuropathy involving cranial nerves\n6. Lupus headache: Severe, persistent headache (may be migrainous but must be nonresponsive to narcotic analgesia).\n7. New onset stroke: Exclude arteriosclerosis.\n8. Vasculitis: Ulceration, gangrene, tender finger nodules, periungual infarction, splinter hemorrhages or biopsy, and angiogram proof of vasculitis.\n9. Arthritis: ≥2 joints with pain and signs of inflammation (i.e., tenderness, swelling, or effusion).\n10. Myositis: Proximal muscle aching/weakness associated with elevated CPK/aldolase, EMG changes, or a biopsy showing myositis.\n11. Heme-granular or RBC urinary casts\n12. Hematuria: >5 RBC/high-power field; exclude stone, infection, or other cause.\n13. Proteinuria: >0.5 g/24 hours.\n14. Pyuria: >5 WBC/high-power field; exclude infection.\n15. Inflammatory-type rash.\n16. Alopecia.\n17. Oral or nasal mucosal ulcers.\n18. Pleuritic chest pain with pleural rub/effusion or pleural thickening.\n19. Pericarditis: Pericardial pain with ≥1 of the following: rub, effusion, or EKG/echocardiogram confirmation.\n20. Low complement: CH50, C3, or C4 decreased below lower limit of normal for lab.\n21. High DNA binding: Increased above normal range for lab.\n22. Temp >100.4 °F (38°C): Exclude infectious causes.\n23. Platelets <100 x 109/L: Exclude drug causes.\n24. WBC <3 x 109/L: Exclude drug causes.\n\nInterpretation:\nThe most appropriate SLEDAI-2K cut-off score for definition of active disease which links to the need to increase therapy is 3 or 4, and trending changes over time in order to help with decision-making is recommended (Yee 2011).",
        "copyright": "Cambio CDS"
      }
    },
    "other_details": {
      "references": "Gladman DD, Ibañez D, Urowitz MB. Systemic lupus erythematosus disease activity index 2000. J Rheumatol. 2002 Feb;29(2):288-91. PMID: 11838846.\n\nYee CS, Farewell VT, Isenberg DA, Griffiths B, Teh LS, Bruce IN, Ahmad Y, Rahman A, Prabu A, Akil M, McHugh N, Edwards C, D'Cruz D, Khamashta MA, Gordon C. The use of Systemic Lupus Erythematosus Disease Activity Index-2000 to define active disease and minimal clinically meaningful change based on data from a large cohort of systemic lupus erythematosus patients. Rheumatology (Oxford). 2011 May;50(5):982-8. doi: 10.1093/rheumatology/keq376. Epub 2011 Jan 18. PMID: 21245073; PMCID: PMC3077910."
    }
  },
  "definition": {
    "data_bindings": {
      "gt0002": {
        "id": "gt0002",
        "model_id": "openEHR-EHR-OBSERVATION.sledai_2k.v0",
        "template_id": "openEHR-EHR-OBSERVATION.sledai_2k.v0",
        "type": "INPUT",
        "elements": {
          "gt0042": {
            "id": "gt0042",
            "path": "/data[at0001]/events[at0002]/data[at0003]/items[at0004]"
          },
          "gt0043": {
            "id": "gt0043",
            "path": "/data[at0001]/events[at0002]/data[at0003]/items[at0007]"
          },
          "gt0044": {
            "id": "gt0044",
            "path": "/data[at0001]/events[at0002]/data[at0003]/items[at0010]"
          },
          "gt0045": {
            "id": "gt0045",
            "path": "/data[at0001]/events[at0002]/data[at0003]/items[at0013]"
          },
          "gt0046": {
            "id": "gt0046",
            "path": "/data[at0001]/events[at0002]/data[at0003]/items[at0016]"
          },
          "gt0047": {
            "id": "gt0047",
            "path": "/data[at0001]/events[at0002]/data[at0003]/items[at0019]"
          },
          "gt0048": {
            "id": "gt0048",
            "path": "/data[at0001]/events[at0002]/data[at0003]/items[at0020]"
          },
          "gt0049": {
            "id": "gt0049",
            "path": "/data[at0001]/events[at0002]/data[at0003]/items[at0021]"
          },
          "gt0050": {
            "id": "gt0050",
            "path": "/data[at0001]/events[at0002]/data[at0003]/items[at0022]"
          },
          "gt0051": {
            "id": "gt0051",
            "path": "/data[at0001]/events[at0002]/data[at0003]/items[at0023]"
          },
          "gt0052": {
            "id": "gt0052",
            "path": "/data[at0001]/events[at0002]/data[at0003]/items[at0024]"
          },
          "gt0053": {
            "id": "gt0053",
            "path": "/data[at0001]/events[at0002]/data[at0003]/items[at0025]"
          },
          "gt0054": {
            "id": "gt0054",
            "path": "/data[at0001]/events[at0002]/data[at0003]/items[at0026]"
          },
          "gt0055": {
            "id": "gt0055",
            "path": "/data[at0001]/events[at0002]/data[at0003]/items[at0027]"
          },
          "gt0056": {
            "id": "gt0056",
            "path": "/data[at0001]/events[at0002]/data[at0003]/items[at0028]"
          },
          "gt0057": {
            "id": "gt0057",
            "path": "/data[at0001]/events[at0002]/data[at0003]/items[at0029]"
          },
          "gt0058": {
            "id": "gt0058",
            "path": "/data[at0001]/events[at0002]/data[at0003]/items[at0030]"
          },
          "gt0059": {
            "id": "gt0059",
            "path": "/data[at0001]/events[at0002]/data[at0003]/items[at0031]"
          },
          "gt0060": {
            "id": "gt0060",
            "path": "/data[at0001]/events[at0002]/data[at0003]/items[at0032]"
          },
          "gt0061": {
            "id": "gt0061",
            "path": "/data[at0001]/events[at0002]/data[at0003]/items[at0033]"
          },
          "gt0062": {
            "id": "gt0062",
            "path": "/data[at0001]/events[at0002]/data[at0003]/items[at0034]"
          },
          "gt0063": {
            "id": "gt0063",
            "path": "/data[at0001]/events[at0002]/data[at0003]/items[at0035]"
          },
          "gt0064": {
            "id": "gt0064",
            "path": "/data[at0001]/events[at0002]/data[at0003]/items[at0036]"
          },
          "gt0065": {
            "id": "gt0065",
            "path": "/data[at0001]/events[at0002]/data[at0003]/items[at0037]"
          }
        }
      },
      "gt0024": {
        "id": "gt0024",
        "model_id": "openEHR-EHR-OBSERVATION.sledai_2k.v0",
        "template_id": "openEHR-EHR-OBSERVATION.sledai_2k.v0",
        "type": "OUTPUT",
        "elements": {
          "gt0066": {
            "id": "gt0066",
            "path": "/data[at0001]/events[at0002]/data[at0003]/items[at0038]"
          }
        }
      },
      "gt0025": {
        "id": "gt0025",
        "model_id": "openEHR-EHR-EVALUATION.sledai_2k_assessment.v0",
        "template_id": "openEHR-EHR-EVALUATION.sledai_2k_assessment.v0",
        "type": "OUTPUT",
        "elements": {
          "gt0067": {
            "id": "gt0067",
            "path": "/data[at0001]/items[at0002]"
          }
        }
      }
    },
    "rules": {
      "gt0068": {
        "id": "gt0068",
        "priority": 1,
        "when": [
          "$gt0042|Recent onset seizure|!=null",
          "$gt0043|Psychosis|!=null",
          "$gt0044|Organic brain syndrome|!=null",
          "$gt0045|Visual disturbance|!=null",
          "$gt0046|New onset sensory or motor neuropathy involving cranial nerves|!=null",
          "$gt0047|Lupus headache|!=null",
          "$gt0048|New onset stroke|!=null",
          "$gt0049|Vasculitis|!=null",
          "$gt0050|Arthritis|!=null",
          "$gt0051|Myositis|!=null",
          "$gt0052|Heme-granular or RBC urinary casts|!=null",
          "$gt0053|Hematuria|!=null",
          "$gt0054|Proteinuria|!=null",
          "$gt0055|Pyuria|!=null",
          "$gt0056|Inflammatory-type rash|!=null",
          "$gt0057|Alopecia|!=null",
          "$gt0058|Oral or nasal mucosal ulcers|!=null",
          "$gt0059|Pleuritic chest pain with pleural rub/effusion or pleural thickening|!=null",
          "$gt0060|Pericarditis|!=null",
          "$gt0061|Low complement|!=null",
          "$gt0062|High DNA binding|!=null",
          "$gt0063|Temp >100.4 °F (38°C)|!=null",
          "$gt0064|Platelets <100 x 109/L|!=null",
          "$gt0065|WBC <3 x 109/L|!=null"
        ],
        "then": [
          "$gt0066|SLEDAI-2K|.magnitude=$gt0042.value+$gt0043.value+$gt0044.value+$gt0045.value+$gt0046.value+$gt0047.value+$gt0048.value+$gt0049.value+$gt0050.value+$gt0051.value+$gt0052.value+$gt0053.value+$gt0054.value+$gt0055.value+$gt0056.value+$gt0057.value+$gt0058.value+$gt0059.value+$gt0060.value+$gt0061.value+$gt0062.value+$gt0063.value+$gt0064.value+$gt0065.value",
          "$gt0067|Interpretation|='Authors recommend a cutoff of 3 or 4 to define active disease and the need to increase therapy.'"
        ]
      }
    }
  },
  "ontology": {
    "term_definitions": {
      "en": {
        "id": "en",
        "terms": {
          "gt0001": {
            "id": "gt0001",
            "text": "Systemic Lupus Erythematosus Disease Activity Index 2000 (SLEDAI-2K)",
            "description": "The calculated Systemic Lupus Erythematosus Disease Activity Index 2000 (SLEDAI-2K) in patients."
          },
          "gt0003": {
            "id": "gt0003",
            "text": "Recent onset seizure",
            "description": "Exclude metabolic, infectious, or drug causes."
          },
          "gt0004": {
            "id": "gt0004",
            "text": "Psychosis",
            "description": "Altered ability to function in normal activity due to severe disturbance in the perception of reality (include hallucinations, incoherence, marked loose associations, impoverished thought content, marked illogical thinking, and bizarre, disorganized, or catatonic behavior); exclude uremia and drug causes."
          },
          "gt0005": {
            "id": "gt0005",
            "text": "Organic brain syndrome",
            "description": "Altered mental function with impaired orientation, memory, or other intellectual function (with rapid onset and fluctuating clinical features), inability to sustain attention to environment, and ≥2 of the following: perceptual disturbance, incoherent speech, insomnia or daytime drowsiness, and increased or decreased psychomotor activity; exclude metabolic, infectious, or drug causes."
          },
          "gt0006": {
            "id": "gt0006",
            "text": "Visual disturbance",
            "description": "Retinal changes of SLE (include cytoid bodies, retinal hemorrhages, serous exudates or hemorrhages in choroid, and optic neuritis); exclude hypertensive, infectious, or drug causes."
          },
          "gt0007": {
            "id": "gt0007",
            "text": "New onset sensory or motor neuropathy involving cranial nerves",
            "description": "*"
          },
          "gt0008": {
            "id": "gt0008",
            "text": "Lupus headache",
            "description": "Severe, persistent headache (may be migrainous but must be nonresponsive to narcotic analgesia)."
          },
          "gt0009": {
            "id": "gt0009",
            "text": "New onset stroke",
            "description": "Exclude arteriosclerosis."
          },
          "gt0010": {
            "id": "gt0010",
            "text": "Vasculitis",
            "description": "Ulceration, gangrene, tender finger nodules, periungual infarction, splinter hemorrhages or biopsy, and angiogram proof of vasculitis."
          },
          "gt0011": {
            "id": "gt0011",
            "text": "Arthritis",
            "description": "≥2 joints with pain and signs of inflammation (i.e., tenderness, swelling, or effusion)"
          },
          "gt0012": {
            "id": "gt0012",
            "text": "Myositis",
            "description": "Proximal muscle aching/weakness associated with elevated CPK/aldolase, EMG changes, or a biopsy showing myositis."
          },
          "gt0013": {
            "id": "gt0013",
            "text": "Heme-granular or RBC urinary casts",
            "description": "*"
          },
          "gt0014": {
            "id": "gt0014",
            "text": "Hematuria",
            "description": ">5 RBC/high-power field; exclude stone, infection, or other cause."
          },
          "gt0015": {
            "id": "gt0015",
            "text": "Proteinuria",
            "description": ">0.5 g/24 hours."
          },
          "gt0016": {
            "id": "gt0016",
            "text": "Pyuria",
            "description": ">5 WBC/high-power field; exclude infection."
          },
          "gt0017": {
            "id": "gt0017",
            "text": "Inflammatory-type rash",
            "description": "*"
          },
          "gt0018": {
            "id": "gt0018",
            "text": "Alopecia",
            "description": "*"
          },
          "gt0019": {
            "id": "gt0019",
            "text": "Oral or nasal mucosal ulcers",
            "description": "*"
          },
          "gt0020": {
            "id": "gt0020",
            "text": "Pleuritic chest pain with pleural rub/effusion or pleural thickening",
            "description": "*"
          },
          "gt0021": {
            "id": "gt0021",
            "text": "Pericarditis",
            "description": "Pericardial pain with ≥1 of the following: rub, effusion, or EKG/echocardiogram confirmation."
          },
          "gt0022": {
            "id": "gt0022",
            "text": "Low complement",
            "description": "CH50, C3, or C4 decreased below lower limit of normal for lab."
          },
          "gt0023": {
            "id": "gt0023",
            "text": "High DNA binding",
            "description": "Increased above normal range for lab."
          },
          "gt0030": {
            "id": "gt0030",
            "text": "WBC <3 x 109/L",
            "description": "Exclude drug causes."
          },
          "gt0033": {
            "id": "gt0033",
            "text": "Platelet count",
            "description": "The number of platelets per liter"
          },
          "gt0035": {
            "id": "gt0035",
            "text": "Temperature",
            "description": "The measured body temperature (as a surrogate for the whole body)."
          },
          "gt0042": {
            "id": "gt0042",
            "text": "Recent onset seizure",
            "description": "Exclude metabolic, infectious, or drug causes."
          },
          "gt0043": {
            "id": "gt0043",
            "text": "Psychosis",
            "description": "Altered ability to function in normal activity due to severe disturbance in the perception of reality (include hallucinations, incoherence, marked loose associations, impoverished thought content, marked illogical thinking, and bizarre, disorganized, or catatonic behavior); exclude uremia and drug causes."
          },
          "gt0044": {
            "id": "gt0044",
            "text": "Organic brain syndrome",
            "description": "Altered mental function with impaired orientation, memory, or other intellectual function (with rapid onset and fluctuating clinical features), inability to sustain attention to environment, and ≥2 of the following: perceptual disturbance, incoherent speech, insomnia or daytime drowsiness, and increased or decreased psychomotor activity; exclude metabolic, infectious, or drug causes."
          },
          "gt0045": {
            "id": "gt0045",
            "text": "Visual disturbance",
            "description": "Retinal changes of SLE (include cytoid bodies, retinal hemorrhages, serous exudates or hemorrhages in choroid, and optic neuritis); exclude hypertensive, infectious, or drug causes."
          },
          "gt0046": {
            "id": "gt0046",
            "text": "New onset sensory or motor neuropathy involving cranial nerves",
            "description": "*"
          },
          "gt0047": {
            "id": "gt0047",
            "text": "Lupus headache",
            "description": "Severe, persistent headache (may be migrainous but must be nonresponsive to narcotic analgesia)."
          },
          "gt0048": {
            "id": "gt0048",
            "text": "New onset stroke",
            "description": "Exclude arteriosclerosis."
          },
          "gt0049": {
            "id": "gt0049",
            "text": "Vasculitis",
            "description": "Ulceration, gangrene, tender finger nodules, periungual infarction, splinter hemorrhages or biopsy, and angiogram proof of vasculitis."
          },
          "gt0050": {
            "id": "gt0050",
            "text": "Arthritis",
            "description": "≥2 joints with pain and signs of inflammation (i.e., tenderness, swelling, or effusion)"
          },
          "gt0051": {
            "id": "gt0051",
            "text": "Myositis",
            "description": "Proximal muscle aching/weakness associated with elevated CPK/aldolase, EMG changes, or a biopsy showing myositis."
          },
          "gt0052": {
            "id": "gt0052",
            "text": "Heme-granular or RBC urinary casts",
            "description": "*"
          },
          "gt0053": {
            "id": "gt0053",
            "text": "Hematuria",
            "description": ">5 RBC/high-power field; exclude stone, infection, or other cause."
          },
          "gt0054": {
            "id": "gt0054",
            "text": "Proteinuria",
            "description": ">0.5 g/24 hours."
          },
          "gt0055": {
            "id": "gt0055",
            "text": "Pyuria",
            "description": ">5 WBC/high-power field; exclude infection."
          },
          "gt0056": {
            "id": "gt0056",
            "text": "Inflammatory-type rash",
            "description": "*"
          },
          "gt0057": {
            "id": "gt0057",
            "text": "Alopecia",
            "description": "*"
          },
          "gt0058": {
            "id": "gt0058",
            "text": "Oral or nasal mucosal ulcers",
            "description": "*"
          },
          "gt0059": {
            "id": "gt0059",
            "text": "Pleuritic chest pain with pleural rub/effusion or pleural thickening",
            "description": "*"
          },
          "gt0060": {
            "id": "gt0060",
            "text": "Pericarditis",
            "description": "Pericardial pain with ≥1 of the following: rub, effusion, or EKG/echocardiogram confirmation."
          },
          "gt0061": {
            "id": "gt0061",
            "text": "Low complement",
            "description": "CH50, C3, or C4 decreased below lower limit of normal for lab."
          },
          "gt0062": {
            "id": "gt0062",
            "text": "High DNA binding",
            "description": "Increased above normal range for lab."
          },
          "gt0063": {
            "id": "gt0063",
            "text": "Temp >100.4 °F (38°C)",
            "description": "Exclude infectious causes."
          },
          "gt0064": {
            "id": "gt0064",
            "text": "Platelets <100 x 109/L",
            "description": "Exclude drug causes."
          },
          "gt0065": {
            "id": "gt0065",
            "text": "WBC <3 x 109/L",
            "description": "Exclude drug causes."
          },
          "gt0066": {
            "id": "gt0066",
            "text": "SLEDAI-2K",
            "description": "*"
          },
          "gt0067": {
            "id": "gt0067",
            "text": "Interpretation",
            "description": "*"
          },
          "gt0068": {
            "id": "gt0068",
            "text": "Calculate SLEDAI-2K"
          }
        }
      }
    }
  }
}