<?xml version="1.0" encoding="utf-8"?>
<StructureDefinition xmlns="http://hl7.org/fhir">
  <id value="FHIR-STU3-ProcedureRequest.generic.v0" />
  <meta>
    <lastUpdated value="2018-01-19T00:22:59.699+01:00" />
  </meta>
  <url value="https://tools.cambiocds.com/FHIR/StructureDefinition/FHIR-STU3-ProcedureRequest.generic.v0" />
  <name value="org.hl7.fhir.dstu3.model.ProcedureRequest" />
  <status value="draft" />
  <date value="2017-12-23T00:52:27.17+01:00" />
  <fhirVersion value="3.0.1" />
  <kind value="resource" />
  <abstract value="false" />
  <type value="ProcedureRequest" />
  <baseDefinition value="http://hl7.org/fhir/StructureDefinition/ProcedureRequest" />
  <derivation value="constraint" />
  <differential>
    <element id="ProcedureRequest.extension">
      <path value="ProcedureRequest.extension" />
      <slicing>
        <discriminator>
          <type value="value" />
          <path value="url" />
        </discriminator>
        <rules value="open" />
      </slicing>
    </element>
    <element id="ProcedureRequest.extension:description">
      <path value="ProcedureRequest.extension" />
      <sliceName value="description" />
      <short value="String value associated with ProcedureRequest" />
      <definition value="A string value associated with the ProcedureRequest resource." />
      <max value="1" />
      <type>
        <code value="Extension" />
        <profile value="https://gitlab.cambiocds.com/CDS-PLATFORM/c3cloud-cdsm/blob/resource_profiles/src/main/resources/extensions/extension-ProcedureRequest-description-string-value.xml" />
      </type>
    </element>
    <element id="ProcedureRequest.extension:description.url">
      <path value="ProcedureRequest.extension.url" />
      <fixedUri value="https://gitlab.cambiocds.com/CDS-PLATFORM/c3cloud-cdsm/blob/resource_profiles/src/main/resources/extensions/extension-ProcedureRequest-description-string-value.xml" />
    </element>
    <element id="ProcedureRequest.extension:description.valueString:valueString">
      <path value="ProcedureRequest.extension.valueString" />
      <sliceName value="valueString" />
      <type>
        <code value="string" />
        <profile value="http://hl7.org/fhir/StructureDefinition/string" />
      </type>
    </element>
    <element id="ProcedureRequest.status">
      <path value="ProcedureRequest.status" />
      <type>
        <code value="code" />
        <profile value="http://hl7.org/fhir/StructureDefinition/code" />
      </type>
      <fixedCode value="draft | active | suspended | completed | entered-in-error | cancelled" />
    </element>
    <element id="ProcedureRequest.intent">
      <path value="ProcedureRequest.intent" />
      <type>
        <code value="code" />
        <profile value="http://hl7.org/fhir/StructureDefinition/code" />
      </type>
      <fixedCode value="proposal | plan | order | original-order | reflex-order | filler-order | instance-order | option" />
    </element>
    <element id="ProcedureRequest.category.coding">
      <path value="ProcedureRequest.category.coding" />
      <type>
        <code value="Coding" />
        <profile value="http://hl7.org/fhir/StructureDefinition/Coding" />
      </type>
    </element>
    <element id="ProcedureRequest.category.text">
      <extension url="http://hl7.org/fhir/StructureDefinition/elementdefinition-translatable">
        <valueBoolean value="true" />
      </extension>
      <path value="ProcedureRequest.category.text" />
      <type>
        <code value="string" />
        <profile value="http://hl7.org/fhir/StructureDefinition/string" />
      </type>
    </element>
    <element id="ProcedureRequest.code.coding">
      <path value="ProcedureRequest.code.coding" />
      <type>
        <code value="Coding" />
        <profile value="http://hl7.org/fhir/StructureDefinition/Coding" />
      </type>
    </element>
    <element id="ProcedureRequest.code.text">
      <extension url="http://hl7.org/fhir/StructureDefinition/elementdefinition-translatable">
        <valueBoolean value="true" />
      </extension>
      <path value="ProcedureRequest.code.text" />
      <type>
        <code value="string" />
        <profile value="http://hl7.org/fhir/StructureDefinition/string" />
      </type>
    </element>
    <element id="ProcedureRequest.occurrenceTiming:occurrenceTiming">
      <path value="ProcedureRequest.occurrenceTiming" />
      <sliceName value="occurrenceTiming" />
      <type>
        <code value="Timing" />
      </type>
    </element>
    <element id="ProcedureRequest.occurrenceTiming:occurrenceTiming.code.coding">
      <path value="ProcedureRequest.occurrenceTiming.code.coding" />
      <type>
        <code value="Coding" />
        <profile value="http://hl7.org/fhir/StructureDefinition/Coding" />
      </type>
    </element>
    <element id="ProcedureRequest.occurrenceTiming:occurrenceTiming.code.text">
      <extension url="http://hl7.org/fhir/StructureDefinition/elementdefinition-translatable">
        <valueBoolean value="true" />
      </extension>
      <path value="ProcedureRequest.occurrenceTiming.code.text" />
      <type>
        <code value="string" />
        <profile value="http://hl7.org/fhir/StructureDefinition/string" />
      </type>
    </element>
    <element id="ProcedureRequest.performer.display">
      <extension url="http://hl7.org/fhir/StructureDefinition/elementdefinition-translatable">
        <valueBoolean value="true" />
      </extension>
      <path value="ProcedureRequest.performer.display" />
      <type>
        <code value="string" />
        <profile value="http://hl7.org/fhir/StructureDefinition/string" />
      </type>
    </element>
  </differential>
</StructureDefinition>